seso.cp38-win_amd64.pyd
seso-0.3.dist-info/LICENSE
seso-0.3.dist-info/METADATA
seso-0.3.dist-info/WHEEL
seso-0.3.dist-info/top_level.txt
seso-0.3.dist-info/RECORD
