Metadata-Version: 2.1
Name: seso
Version: 0.3
Summary: Search and Sort Algorithms
Home-page: https://github.com/AjithRamachandran/seso
Author: Ajith Ramachandran
Author-email: ajithar204@gmail.com
License: MIT
Keywords: search and sort
Platform: UNKNOWN
Classifier: Programming Language :: Python :: 3
Classifier: License :: OSI Approved :: MIT License
Classifier: Operating System :: OS Independent
Classifier: Programming Language :: Python :: Implementation :: CPython
License-File: LICENSE
Requires-Dist: numpy
